madam/__init__.py
madam/_version.py
madam/audio.py
madam/core.py
madam/exif.py
madam/ffmpeg.py
madam/image.py
madam/mime.py
madam/vector.py
madam/video.py
MADAM-0.21.2.dist-info/LICENSE.AGPL
MADAM-0.21.2.dist-info/METADATA
MADAM-0.21.2.dist-info/WHEEL
MADAM-0.21.2.dist-info/top_level.txt
MADAM-0.21.2.dist-info/RECORD
