Metadata-Version: 2.1
Name: MADAM
Version: 0.21.2
Summary: Digital asset management library
Home-page: https://github.com/eseifert/madam
Author: Michael Seifert, Erich Seifert
Author-email: mseifert@error-reports.org, dev@erichseifert.de
License: AGPLv3
Keywords: asset media processing
Platform: POSIX
Classifier: Development Status :: 4 - Beta
Classifier: Environment :: Console
Classifier: Intended Audience :: Developers
Classifier: Operating System :: POSIX
Classifier: Programming Language :: Python
Classifier: Topic :: Multimedia :: Graphics :: Graphics Conversion
Classifier: Topic :: Multimedia :: Sound/Audio :: Conversion
Classifier: Topic :: Multimedia :: Video :: Conversion
Classifier: License :: OSI Approved :: GNU Affero General Public License v3
Classifier: Programming Language :: Python :: 3 :: Only
Classifier: Programming Language :: Python :: 3.6
Classifier: Programming Language :: Python :: 3.7
Classifier: Programming Language :: Python :: 3.8
Classifier: Programming Language :: Python :: 3.9
Requires-Python: >=3.6
Requires-Dist: bidict
Requires-Dist: frozendict
Requires-Dist: piexif
Requires-Dist: pillow (>=8.2.0)
Requires-Dist: zopflipy (>=1.1)
Provides-Extra: doc
Requires-Dist: sphinx (>=1.3) ; extra == 'doc'
Requires-Dist: sphinx-rtd-theme ; extra == 'doc'
